github_monitor.py
github_monitor-2.4.dist-info/licenses/LICENSE
github_monitor-2.4.dist-info/METADATA
github_monitor-2.4.dist-info/WHEEL
github_monitor-2.4.dist-info/entry_points.txt
github_monitor-2.4.dist-info/top_level.txt
github_monitor-2.4.dist-info/RECORD
